TensorflowLiteMlKitHeFlutterYidongShenduXuexiChuyiFix1/README.md
TensorflowLiteMlKitHeFlutterYidongShenduXuexiChuyiFix1/__init__.py
TensorflowLiteMlKitHeFlutterYidongShenduXuexiChuyiFix1/__main__.py
TensorflowLiteMlKitHeFlutterYidongShenduXuexiChuyiFix1/file.epub
TensorflowLiteMlKitHeFlutterYidongShenduXuexiChuyiFix1/index.html
TensorflowLiteMlKitHeFlutterYidongShenduXuexiChuyiFix1/css/__init__.py
TensorflowLiteMlKitHeFlutterYidongShenduXuexiChuyiFix1/css/annotations.css
TensorflowLiteMlKitHeFlutterYidongShenduXuexiChuyiFix1/css/main.css
TensorflowLiteMlKitHeFlutterYidongShenduXuexiChuyiFix1/css/normalize.css
TensorflowLiteMlKitHeFlutterYidongShenduXuexiChuyiFix1/css/popup.css
TensorflowLiteMlKitHeFlutterYidongShenduXuexiChuyiFix1/font/__init__.py
TensorflowLiteMlKitHeFlutterYidongShenduXuexiChuyiFix1/font/fontello.eot
TensorflowLiteMlKitHeFlutterYidongShenduXuexiChuyiFix1/font/fontello.svg
TensorflowLiteMlKitHeFlutterYidongShenduXuexiChuyiFix1/font/fontello.ttf
TensorflowLiteMlKitHeFlutterYidongShenduXuexiChuyiFix1/font/fontello.woff
TensorflowLiteMlKitHeFlutterYidongShenduXuexiChuyiFix1/img/__init__.py
TensorflowLiteMlKitHeFlutterYidongShenduXuexiChuyiFix1/img/annotator-glyph-sprite.png
TensorflowLiteMlKitHeFlutterYidongShenduXuexiChuyiFix1/img/annotator-icon-sprite.png
TensorflowLiteMlKitHeFlutterYidongShenduXuexiChuyiFix1/img/apple-touch-icon.png
TensorflowLiteMlKitHeFlutterYidongShenduXuexiChuyiFix1/img/cancelfullscreen.png
TensorflowLiteMlKitHeFlutterYidongShenduXuexiChuyiFix1/img/close.png
TensorflowLiteMlKitHeFlutterYidongShenduXuexiChuyiFix1/img/fullscreen.png
TensorflowLiteMlKitHeFlutterYidongShenduXuexiChuyiFix1/img/loader.gif
TensorflowLiteMlKitHeFlutterYidongShenduXuexiChuyiFix1/img/menu-icon.png
TensorflowLiteMlKitHeFlutterYidongShenduXuexiChuyiFix1/img/save.png
TensorflowLiteMlKitHeFlutterYidongShenduXuexiChuyiFix1/img/saved.png
TensorflowLiteMlKitHeFlutterYidongShenduXuexiChuyiFix1/img/settings-s.png
tensorflow_lite_ml_kit_he_flutter_yidong_shendu_xuexi_chuyi_fix1-2025.3.25.0.dist-info/METADATA
tensorflow_lite_ml_kit_he_flutter_yidong_shendu_xuexi_chuyi_fix1-2025.3.25.0.dist-info/WHEEL
tensorflow_lite_ml_kit_he_flutter_yidong_shendu_xuexi_chuyi_fix1-2025.3.25.0.dist-info/entry_points.txt
tensorflow_lite_ml_kit_he_flutter_yidong_shendu_xuexi_chuyi_fix1-2025.3.25.0.dist-info/top_level.txt
tensorflow_lite_ml_kit_he_flutter_yidong_shendu_xuexi_chuyi_fix1-2025.3.25.0.dist-info/RECORD
